voxplayer/__init__.py
voxplayer/app.py
voxplayer/logo.png
voxplayer-1.0.1.dist-info/licenses/LICENSE
voxplayer-1.0.1.dist-info/METADATA
voxplayer-1.0.1.dist-info/WHEEL
voxplayer-1.0.1.dist-info/entry_points.txt
voxplayer-1.0.1.dist-info/top_level.txt
voxplayer-1.0.1.dist-info/RECORD
