Metadata-Version: 2.4
Name: voxplayer
Version: 1.0.1
Summary: A modern multimedia player built with PyQt6
Home-page: https://github.com/voxhash/voxplayer
Author: VoxHash
Author-email: VoxHash <voxhash@example.com>
Maintainer-email: VoxHash <voxhash@example.com>
License: MIT
Project-URL: Homepage, https://github.com/voxhash/voxplayer
Project-URL: Documentation, https://github.com/voxhash/voxplayer#readme
Project-URL: Repository, https://github.com/voxhash/voxplayer.git
Project-URL: Bug Tracker, https://github.com/voxhash/voxplayer/issues
Keywords: media player,video player,audio player,PyQt6,multimedia,playlist,torrent streaming
Classifier: Development Status :: 5 - Production/Stable
Classifier: Intended Audience :: End Users/Desktop
Classifier: Topic :: Multimedia :: Video :: Display
Classifier: Topic :: Multimedia :: Sound/Audio :: Players
Classifier: License :: OSI Approved :: MIT License
Classifier: Programming Language :: Python :: 3
Classifier: Programming Language :: Python :: 3.8
Classifier: Programming Language :: Python :: 3.9
Classifier: Programming Language :: Python :: 3.10
Classifier: Programming Language :: Python :: 3.11
Classifier: Programming Language :: Python :: 3.12
Classifier: Operating System :: Microsoft :: Windows
Classifier: Operating System :: MacOS
Classifier: Operating System :: POSIX :: Linux
Requires-Python: >=3.8
License-File: LICENSE
Requires-Dist: PyQt6>=6.0.0
Requires-Dist: requests>=2.25.0
Provides-Extra: dev
Requires-Dist: pytest>=6.0.0; extra == "dev"
Requires-Dist: black>=21.0.0; extra == "dev"
Requires-Dist: flake8>=3.8.0; extra == "dev"
Requires-Dist: mypy>=0.800; extra == "dev"
Provides-Extra: torrent
Requires-Dist: qbittorrent-api>=0.4.0; extra == "torrent"
Dynamic: author
Dynamic: home-page
Dynamic: license-file
Dynamic: requires-python
